[
    {
        "key": "EVTNAME62951",
        "original": "Ragnarr's Curse",
        "translation": "朗纳尔的诅咒",
        "stage": 5
    },
    {
        "key": "EVTDESC62951",
        "original": "The cowardly king Ælla is kneeling before me in the mud, refusing to meet my eyes. The men call out for various punishments - some more creative than others. I call for silence and a hush descends as the raven banner flutters eagerly above the doomed man. It is time to exact revenge for my dead father, Ragnarr...",
        "translation": "懦弱的埃拉国王跪在我面前的泥滩里，他不敢直视我的眼睛。我的战士们为了好好「招待」他，想出了各种别出心裁的刑罚。我让大家安静下来，顿时四周一片肃穆，但众人的心情都如同在风中鼓动的金乌旗帜一般，他们渴求终结这个大难临头的家伙的性命。现在是为我死去的父亲——郎纳尔复仇的时刻了……",
        "stage": 5
    },
    {
        "key": "EVTOPTA62951",
        "original": "Carve the Blood Eagle!",
        "translation": "执行血鹰之刑！",
        "stage": 5
    },
    {
        "key": "EVTOPTB62951",
        "original": "Sacrifice him to Odin!",
        "translation": "把他献祭给奥丁！",
        "stage": 5
    },
    {
        "key": "EVTOPTC62951",
        "original": "Four balls for the Ravens!",
        "translation": "把他身上的四个球献给奥丁的乌鸦！",
        "stage": 5
    },
    {
        "key": "EVTOPTD62951",
        "original": "I have other plans for Ælla...",
        "translation": "我对埃拉另有处置……",
        "stage": 5
    },
    {
        "key": "EVTDESC62952",
        "original": "The last thing I saw before the heathen savages carved out my eyes was the horrible grin on [From.GetFirstName]'s face. I tried to curl up as they prepared to unman me...",
        "translation": "在我被这群野蛮人挖掉双眼前的最后一刻，我看到的是[From.GetFirstName]脸上那残酷而恐怖的笑容。我试着蜷缩起来，因为他们打算要阉了我……",
        "stage": 5
    },
    {
        "key": "EVTOPTA62952",
        "original": "ARRRRGH!",
        "translation": "啊啊啊啊啊啊！",
        "stage": 5
    },
    {
        "key": "AIREASON_IN_OTHER_WAR",
        "original": "In Other War",
        "translation": "处于另一场战争",
        "stage": 5
    },
    {
        "key": "AIREASON_BUSY_RAIDING",
        "original": "Raiding",
        "translation": "劫掠",
        "stage": 5
    },
    {
        "key": "WRONG_RELIGION_MODIFIER",
        "original": "Wrong Religion",
        "translation": "错误的宗教",
        "stage": 5
    },
    {
        "key": "WRONG_CULTURE_MODIFIER",
        "original": "Wrong Culture",
        "translation": "错误的文化",
        "stage": 5
    },
    {
        "key": "opinion_infidel_tribal_liege",
        "original": "Infidel",
        "translation": "异教徒",
        "stage": 5
    },
    {
        "key": "opinion_heretic_tribal_liege",
        "original": "Heretic",
        "translation": "异端",
        "stage": 5
    },
    {
        "key": "opinion_related_religion_tribal_liege",
        "original": "Religious Differences",
        "translation": "宗教差异",
        "stage": 5
    },
    {
        "key": "AIREASON_TRIBAL_VASSAL_PRESTIGE_HIT",
        "original": "Would cost me too much prestige",
        "translation": "将会消耗我过多的威望",
        "stage": 5
    },
    {
        "key": "opinion_granted_other_vice_royalty",
        "original": "Feudal opinion of granted Viceroyalties",
        "translation": "封建领主对任命总督一事的看法",
        "stage": 5
    },
    {
        "key": "GRANT_VICE_ROYALTY_INTERACTION_8",
        "original": "Granting a Viceroyalty will lower all of your feudal duke and king subjects' opinion of you by §R$OPINION$§!.",
        "translation": "任命总督会降低你所有封建公爵或以上封臣对你的好感：§R$OPINION$§!。",
        "stage": 5
    },
    {
        "key": "NOT_ANY_PREVIOUS_HOLDER_STARTS",
        "original": "No Previous Holder",
        "translation": "并无前任",
        "stage": 5
    },
    {
        "key": "tribal_build_zeal_ARMY_OF",
        "original": "$RELIGION$ Zealots of $CHARACTER$",
        "translation": "$CHARACTER$的$RELIGION$狂热者",
        "stage": 5
    },
    {
        "key": "tribal_organize_raid_ARMY_OF",
        "original": "Raiders of $CHARACTER$",
        "translation": "$CHARACTER$的劫掠者",
        "stage": 5
    },
    {
        "key": "tribal_build_legend_ARMY_OF",
        "original": "Warriors of $CHARACTER$",
        "translation": "$CHARACTER$的战士",
        "stage": 5
    },
    {
        "key": "tribal_build_zeal_ARMY",
        "original": "$RELIGION$ Zealots",
        "translation": "$RELIGION$的狂热者",
        "stage": 5
    },
    {
        "key": "tribal_organize_raid_ARMY",
        "original": "Raiders",
        "translation": "劫掠者",
        "stage": 5
    },
    {
        "key": "tribal_build_legend_ARMY",
        "original": "Warriors",
        "translation": "战士",
        "stage": 5
    },
    {
        "key": "expel_saint_anthony",
        "original": "Expel the Order of Saint Anthony",
        "translation": "驱逐圣安东尼骑士团",
        "stage": 5
    },
    {
        "key": "expel_saint_anthony_desc",
        "original": "I can drive the Order of Saint Anthony from my realm and seize their castles. However, it is a very impious thing to do...",
        "translation": "我可以将圣安东尼骑士团从我的国土上赶走并霸占他们的领地。但这么做是对神灵的亵渎……",
        "stage": 5
    },
    {
        "key": "ISNT_CROWN_LAW_TITLE",
        "original": "Is not a Crown Law title",
        "translation": "不是王权法头衔",
        "stage": 5
    },
    {
        "key": "IS_CROWN_LAW_TITLE",
        "original": "Is a Crown Law title",
        "translation": "是王权法头衔",
        "stage": 5
    },
    {
        "key": "LAW_UNLOCKS",
        "original": "Laws unlocked: ",
        "translation": "解锁法律：",
        "stage": 5
    },
    {
        "key": "DECISION_UNLOCKS",
        "original": "Decisions unlocked: ",
        "translation": "解锁决议：",
        "stage": 5
    },
    {
        "key": "ALLOW_FREE_DUCHY_REVOKATION_ON",
        "original": "Revocation of duchy titles free.\\n",
        "translation": "可以无偿剥夺公爵头衔。\\n",
        "stage": 5
    },
    {
        "key": "ALLOW_FREE_DUCHY_REVOKATION_OFF",
        "original": "Revocation of duchy titles no longer free.\\n",
        "translation": "不可无偿剥夺公爵头衔。\\n",
        "stage": 5
    },
    {
        "key": "LIEGE_LEVY_DESC_VICE_ROY",
        "original": "\\n   Viceroyalty: $VALUE$",
        "translation": "\\n   总督：$VALUE$",
        "stage": 5
    },
    {
        "key": "TITLE_NOT_VICE_ROYALTY",
        "original": "Title is not a Viceroyalty",
        "translation": "头衔不是总督",
        "stage": 5
    },
    {
        "key": "tribal_king_female",
        "original": "Queen",
        "translation": "女王",
        "stage": 5
    },
    {
        "key": "tribal_emperor_female",
        "original": "Empress",
        "translation": "女皇",
        "stage": 5
    },
    {
        "key": "temple_duke_female_pagan_group",
        "original": "Archpriestess",
        "translation": "女大祭司",
        "stage": 5
    },
    {
        "key": "temple_king_female_pagan_group",
        "original": "Queen-Priestess",
        "translation": "巫后",
        "stage": 5
    },
    {
        "key": "temple_emperor_female_pagan_group",
        "original": "Empress",
        "translation": "女巫帝",
        "stage": 5
    },
    {
        "key": "AIREASON_SAME_RELIGION_AS_REGENT",
        "original": "Same religion as me",
        "translation": "和我同属一个宗教",
        "stage": 5
    },
    {
        "key": "expel_the_haruriyyah",
        "original": "Expel the Haruriyyah",
        "translation": "驱逐哈里鲁耶派",
        "stage": 5
    },
    {
        "key": "expel_the_haruriyyah_desc",
        "original": "I can drive the Haruriyyah from my realm and seize their castles. However, it is a very impious thing to do...",
        "translation": "我可以将哈里鲁耶派从我的国土上赶走并霸占他们的领地。但这么做是对神灵的亵渎……",
        "stage": 5
    },
    {
        "key": "borrow_money_haruriyyah",
        "original": "Borrow 300¤ from the Haruriyyah",
        "translation": "向哈里鲁耶派借 300¤",
        "stage": 5
    },
    {
        "key": "borrow_money_haruriyyah_desc",
        "original": "I can borrow money from the Haruriyyah and pay back the same sum at any time. However, while I'm in their debt, the Grand Master can make various requests, like one of my sons joining their ranks.",
        "translation": "我可以向哈里鲁耶派借一些无息无期贷款，但是在我欠钱期间，他们的大长老会向我提出各种各样的要求，比如让我的一个儿子加入他们的行列。",
        "stage": 5
    },
    {
        "key": "not_shia_caliphate_revolt_ongoing",
        "original": "No ongoing revolt to create the Shia Caliphate",
        "translation": "没有爆发拥立什叶派哈里发的叛乱",
        "stage": 5
    },
    {
        "key": "shia_creation_independent",
        "original": "Either independent or all lieges Shia\\n",
        "translation": "要么独立，要么所有封君都信仰什叶派\\n",
        "stage": 5
    },
    {
        "key": "sunni_creation_independent",
        "original": "Either independent or all lieges Sunni\\n",
        "translation": "要么独立，要么所有封君都信仰逊尼派\\n",
        "stage": 5
    }
]